{
  "batch": {
    "id": "phase1-light-social-batch01",
    "titleZh": "晚宴流光首批 40 条采样",
    "occasionId": "light-social",
    "status": "collecting",
    "themeKeys": [
      "light-social-glow",
      "light-social-modern-romance",
      "light-social-polished-dinner",
      "light-social-sage-polish",
      "light-social-night-navy"
    ],
    "sourceWhitelistIds": [
      "brand-site",
      "brand-flagship-store",
      "multi-brand-platform",
      "marketplace-brand-store"
    ],
    "notes": "晚宴流光场景首批骨架，用于生成轻约会、聚餐与朋友见面方向的女装配色候选。"
  },
  "items": [
    {
      "accentColorSummary": "暖砖红",
      "brandName": "SEZANE",
      "candidatePaletteIds": [],
      "channelType": "brand-site",
      "colorSummary": [
        "海雾蓝",
        "柔卡其",
        "暖砖红"
      ],
      "digestionStatus": "sampled",
      "finalPaletteIds": [],
      "itemCategory": "blouse",
      "marketSignals": "轻社交场景需要一点提气，但仍以低饱和豆沙、雾粉杏和奶白为主，避免甜腻。 SEZANE 更适合柔和提气与女性化但不甜腻的通勤路线。",
      "notes": "自动候选：优先审阅 SEZANE 的 SEZANE 官网 入口，重点看 海雾蓝、柔卡其与暖砖红的轻社交提气层次。",
      "observedAt": "2026-05-09",
      "occasionId": "light-social",
      "platform": "SEZANE 官网",
      "primaryColorSummary": "海雾蓝",
      "productionBatchId": "phase1-light-social-batch01",
      "samplingId": "sam_light-social_b01_001",
      "seasonHint": "spring",
      "secondaryColorSummary": "柔卡其",
      "sourceId": "candidate-sezane-blouse-sam_light-social_b01_001",
      "sourceUrl": "https://www.sezane.com/",
      "styleSignals": [
        "soft",
        "feminine-leaning",
        "womenswear"
      ],
      "themeKey": "light-social-glow",
      "themeLabelZh": "轻社交微光提气"
    },
    {
      "accentColorSummary": "焦糖棕",
      "brandName": "SEZANE",
      "candidatePaletteIds": [],
      "channelType": "brand-flagship-store",
      "colorSummary": [
        "海雾蓝",
        "霜白",
        "焦糖棕"
      ],
      "digestionStatus": "sampled",
      "finalPaletteIds": [],
      "itemCategory": "blouse",
      "marketSignals": "轻约会和朋友见面更适合把柔粉压进灰感，做成更成熟的现代柔美路线。 SEZANE 更适合柔和提气与女性化但不甜腻的通勤路线。",
      "notes": "自动候选：优先审阅 SEZANE 的 SEZANE 公开品牌检索 入口，重点看 海雾蓝、霜白与焦糖棕的现代柔美层次。",
      "observedAt": "2026-05-09",
      "occasionId": "light-social",
      "platform": "SEZANE 公开品牌检索",
      "primaryColorSummary": "海雾蓝",
      "productionBatchId": "phase1-light-social-batch01",
      "samplingId": "sam_light-social_b01_002",
      "seasonHint": "spring",
      "secondaryColorSummary": "霜白",
      "sourceId": "candidate-sezane-blouse-sam_light-social_b01_002",
      "sourceUrl": "https://www.google.com/search?q=SEZANE%20women%20blouse%20women%20official%20brand%20search",
      "styleSignals": [
        "soft",
        "feminine-leaning",
        "womenswear"
      ],
      "themeKey": "light-social-modern-romance",
      "themeLabelZh": "轻社交现代柔美"
    },
    {
      "accentColorSummary": "榛棕",
      "brandName": "Theory",
      "candidatePaletteIds": [],
      "channelType": "multi-brand-platform",
      "colorSummary": [
        "奶雾白",
        "深雾灰",
        "榛棕"
      ],
      "digestionStatus": "sampled",
      "finalPaletteIds": [],
      "itemCategory": "blouse",
      "marketSignals": "轻晚餐和轻社交不一定都是粉色，珍珠白、烟灰蓝与李紫灰能把精致感拉出来。 Theory 更适合剪裁明确、冷静专业的女装通勤样本。",
      "notes": "自动候选：优先审阅 Theory 的 Net-a-Porter 公开检索 入口，重点看 奶雾白、深雾灰与榛棕的精致晚餐层次。",
      "observedAt": "2026-05-09",
      "occasionId": "light-social",
      "platform": "Net-a-Porter 公开检索",
      "primaryColorSummary": "奶雾白",
      "productionBatchId": "phase1-light-social-batch01",
      "samplingId": "sam_light-social_b01_003",
      "seasonHint": "spring",
      "secondaryColorSummary": "深雾灰",
      "sourceId": "candidate-theory-blouse-sam_light-social_b01_003",
      "sourceUrl": "https://www.google.com/search?q=site%3Anet-a-porter.com%20Theory%20women%20blouse",
      "styleSignals": [
        "tailored",
        "sharp",
        "womenswear"
      ],
      "themeKey": "light-social-polished-dinner",
      "themeLabelZh": "轻社交精致晚餐"
    },
    {
      "accentColorSummary": "鼠尾草灰",
      "brandName": "SEZANE",
      "candidatePaletteIds": [],
      "channelType": "marketplace-brand-store",
      "colorSummary": [
        "银雾蓝",
        "焦糖棕",
        "鼠尾草灰"
      ],
      "digestionStatus": "sampled",
      "finalPaletteIds": [],
      "itemCategory": "blouse",
      "marketSignals": "轻社交并不总靠粉调，奶油白、浅卡其和鼠尾草灰更适合偏克制的雅致路线。 SEZANE 更适合柔和提气与女性化但不甜腻的通勤路线。",
      "notes": "自动候选：优先审阅 SEZANE 的 SEZANE 公开店铺检索 入口，重点看 银雾蓝、焦糖棕与鼠尾草灰的鼠尾草雅致层次。",
      "observedAt": "2026-05-09",
      "occasionId": "light-social",
      "platform": "SEZANE 公开店铺检索",
      "primaryColorSummary": "银雾蓝",
      "productionBatchId": "phase1-light-social-batch01",
      "samplingId": "sam_light-social_b01_004",
      "seasonHint": "spring",
      "secondaryColorSummary": "焦糖棕",
      "sourceId": "candidate-sezane-blouse-sam_light-social_b01_004",
      "sourceUrl": "https://www.google.com/search?q=SEZANE%20women%20blouse%20women%20outfit%20search",
      "styleSignals": [
        "soft",
        "feminine-leaning",
        "womenswear"
      ],
      "themeKey": "light-social-sage-polish",
      "themeLabelZh": "轻社交鼠尾草雅致"
    },
    {
      "accentColorSummary": "暖砖红",
      "brandName": "TOTEME",
      "candidatePaletteIds": [],
      "channelType": "brand-site",
      "colorSummary": [
        "冰米白",
        "烟炭灰",
        "暖砖红"
      ],
      "digestionStatus": "sampled",
      "finalPaletteIds": [],
      "itemCategory": "blouse",
      "marketSignals": "轻社交的夜间精致路线适合用云雾白、雾灰蓝和墨海军蓝保持克制的存在感。 TOTEME 更适合冷静、低对比、材质感强的女装通勤样本。",
      "notes": "自动候选：优先审阅 TOTEME 的 TOTEME 官网 入口，重点看 冰米白、烟炭灰与暖砖红的夜蓝精致层次。",
      "observedAt": "2026-05-09",
      "occasionId": "light-social",
      "platform": "TOTEME 官网",
      "primaryColorSummary": "冰米白",
      "productionBatchId": "phase1-light-social-batch01",
      "samplingId": "sam_light-social_b01_005",
      "seasonHint": "spring",
      "secondaryColorSummary": "烟炭灰",
      "sourceId": "candidate-toteme-blouse-sam_light-social_b01_005",
      "sourceUrl": "https://toteme.com/",
      "styleSignals": [
        "quiet",
        "refined",
        "womenswear"
      ],
      "themeKey": "light-social-night-navy",
      "themeLabelZh": "轻社交夜蓝精致"
    },
    {
      "accentColorSummary": "赤陶砖红",
      "brandName": "Vince",
      "candidatePaletteIds": [],
      "channelType": "brand-flagship-store",
      "colorSummary": [
        "暖燕麦",
        "海雾蓝",
        "赤陶砖红"
      ],
      "digestionStatus": "sampled",
      "finalPaletteIds": [],
      "itemCategory": "dress",
      "marketSignals": "轻社交场景需要一点提气，但仍以低饱和豆沙、雾粉杏和奶白为主，避免甜腻。 Vince 更适合柔和中性色和都市暖稳路线。",
      "notes": "自动候选：优先审阅 Vince 的 Vince 公开品牌检索 入口，重点看 暖燕麦、海雾蓝与赤陶砖红的轻社交提气层次。",
      "observedAt": "2026-05-09",
      "occasionId": "light-social",
      "platform": "Vince 公开品牌检索",
      "primaryColorSummary": "暖燕麦",
      "productionBatchId": "phase1-light-social-batch01",
      "samplingId": "sam_light-social_b01_006",
      "seasonHint": "spring",
      "secondaryColorSummary": "海雾蓝",
      "sourceId": "candidate-vince-dress-sam_light-social_b01_006",
      "sourceUrl": "https://www.google.com/search?q=Vince%20women%20dress%20women%20official%20brand%20search",
      "styleSignals": [
        "soft",
        "grounded",
        "womenswear"
      ],
      "themeKey": "light-social-glow",
      "themeLabelZh": "轻社交微光提气"
    },
    {
      "accentColorSummary": "板岩灰",
      "brandName": "Vince",
      "candidatePaletteIds": [],
      "channelType": "multi-brand-platform",
      "colorSummary": [
        "沙色卡其",
        "珍珠白",
        "板岩灰"
      ],
      "digestionStatus": "sampled",
      "finalPaletteIds": [],
      "itemCategory": "dress",
      "marketSignals": "轻约会和朋友见面更适合把柔粉压进灰感，做成更成熟的现代柔美路线。 Vince 更适合柔和中性色和都市暖稳路线。",
      "notes": "自动候选：优先审阅 Vince 的 Net-a-Porter 公开检索 入口，重点看 沙色卡其、珍珠白与板岩灰的现代柔美层次。",
      "observedAt": "2026-05-09",
      "occasionId": "light-social",
      "platform": "Net-a-Porter 公开检索",
      "primaryColorSummary": "沙色卡其",
      "productionBatchId": "phase1-light-social-batch01",
      "samplingId": "sam_light-social_b01_007",
      "seasonHint": "spring",
      "secondaryColorSummary": "珍珠白",
      "sourceId": "candidate-vince-dress-sam_light-social_b01_007",
      "sourceUrl": "https://www.google.com/search?q=site%3Anet-a-porter.com%20Vince%20women%20dress",
      "styleSignals": [
        "soft",
        "grounded",
        "womenswear"
      ],
      "themeKey": "light-social-modern-romance",
      "themeLabelZh": "轻社交现代柔美"
    },
    {
      "accentColorSummary": "雾砖红",
      "brandName": "Theory",
      "candidatePaletteIds": [],
      "channelType": "marketplace-brand-store",
      "colorSummary": [
        "雾米白",
        "灰卡其",
        "雾砖红"
      ],
      "digestionStatus": "sampled",
      "finalPaletteIds": [],
      "itemCategory": "dress",
      "marketSignals": "轻晚餐和轻社交不一定都是粉色，珍珠白、烟灰蓝与李紫灰能把精致感拉出来。 Theory 更适合剪裁明确、冷静专业的女装通勤样本。",
      "notes": "自动候选：优先审阅 Theory 的 Theory 公开店铺检索 入口，重点看 雾米白、灰卡其与雾砖红的精致晚餐层次。",
      "observedAt": "2026-05-09",
      "occasionId": "light-social",
      "platform": "Theory 公开店铺检索",
      "primaryColorSummary": "雾米白",
      "productionBatchId": "phase1-light-social-batch01",
      "samplingId": "sam_light-social_b01_008",
      "seasonHint": "spring",
      "secondaryColorSummary": "灰卡其",
      "sourceId": "candidate-theory-dress-sam_light-social_b01_008",
      "sourceUrl": "https://www.google.com/search?q=Theory%20women%20dress%20women%20outfit%20search",
      "styleSignals": [
        "tailored",
        "sharp",
        "womenswear"
      ],
      "themeKey": "light-social-polished-dinner",
      "themeLabelZh": "轻社交精致晚餐"
    },
    {
      "accentColorSummary": "暖咖棕",
      "brandName": "SEZANE",
      "candidatePaletteIds": [],
      "channelType": "brand-site",
      "colorSummary": [
        "暖壳白",
        "暖燕麦",
        "暖咖棕"
      ],
      "digestionStatus": "sampled",
      "finalPaletteIds": [],
      "itemCategory": "dress",
      "marketSignals": "轻社交并不总靠粉调，奶油白、浅卡其和鼠尾草灰更适合偏克制的雅致路线。 SEZANE 更适合柔和提气与女性化但不甜腻的通勤路线。",
      "notes": "自动候选：优先审阅 SEZANE 的 SEZANE 官网 入口，重点看 暖壳白、暖燕麦与暖咖棕的鼠尾草雅致层次。",
      "observedAt": "2026-05-09",
      "occasionId": "light-social",
      "platform": "SEZANE 官网",
      "primaryColorSummary": "暖壳白",
      "productionBatchId": "phase1-light-social-batch01",
      "samplingId": "sam_light-social_b01_009",
      "seasonHint": "spring",
      "secondaryColorSummary": "暖燕麦",
      "sourceId": "candidate-sezane-dress-sam_light-social_b01_009",
      "sourceUrl": "https://www.sezane.com/",
      "styleSignals": [
        "soft",
        "feminine-leaning",
        "womenswear"
      ],
      "themeKey": "light-social-sage-polish",
      "themeLabelZh": "轻社交鼠尾草雅致"
    },
    {
      "accentColorSummary": "岩海军蓝",
      "brandName": "Theory",
      "candidatePaletteIds": [],
      "channelType": "brand-flagship-store",
      "colorSummary": [
        "暖燕麦",
        "冰米白",
        "岩海军蓝"
      ],
      "digestionStatus": "sampled",
      "finalPaletteIds": [],
      "itemCategory": "dress",
      "marketSignals": "轻社交的夜间精致路线适合用云雾白、雾灰蓝和墨海军蓝保持克制的存在感。 Theory 更适合剪裁明确、冷静专业的女装通勤样本。",
      "notes": "自动候选：优先审阅 Theory 的 Theory 公开品牌检索 入口，重点看 暖燕麦、冰米白与岩海军蓝的夜蓝精致层次。",
      "observedAt": "2026-05-09",
      "occasionId": "light-social",
      "platform": "Theory 公开品牌检索",
      "primaryColorSummary": "暖燕麦",
      "productionBatchId": "phase1-light-social-batch01",
      "samplingId": "sam_light-social_b01_010",
      "seasonHint": "spring",
      "secondaryColorSummary": "冰米白",
      "sourceId": "candidate-theory-dress-sam_light-social_b01_010",
      "sourceUrl": "https://www.google.com/search?q=Theory%20women%20dress%20women%20official%20brand%20search",
      "styleSignals": [
        "tailored",
        "sharp",
        "womenswear"
      ],
      "themeKey": "light-social-night-navy",
      "themeLabelZh": "轻社交夜蓝精致"
    },
    {
      "accentColorSummary": "暖咖棕",
      "brandName": "SEZANE",
      "candidatePaletteIds": [],
      "channelType": "multi-brand-platform",
      "colorSummary": [
        "奶驼",
        "铁灰",
        "暖咖棕"
      ],
      "digestionStatus": "sampled",
      "finalPaletteIds": [],
      "itemCategory": "skirt",
      "marketSignals": "轻社交场景需要一点提气，但仍以低饱和豆沙、雾粉杏和奶白为主，避免甜腻。 SEZANE 更适合柔和提气与女性化但不甜腻的通勤路线。",
      "notes": "自动候选：优先审阅 SEZANE 的 Net-a-Porter 公开检索 入口，重点看 奶驼、铁灰与暖咖棕的轻社交提气层次。",
      "observedAt": "2026-05-09",
      "occasionId": "light-social",
      "platform": "Net-a-Porter 公开检索",
      "primaryColorSummary": "奶驼",
      "productionBatchId": "phase1-light-social-batch01",
      "samplingId": "sam_light-social_b01_011",
      "seasonHint": "spring",
      "secondaryColorSummary": "铁灰",
      "sourceId": "candidate-sezane-skirt-sam_light-social_b01_011",
      "sourceUrl": "https://www.google.com/search?q=site%3Anet-a-porter.com%20SEZANE%20women%20skirt",
      "styleSignals": [
        "soft",
        "feminine-leaning",
        "womenswear"
      ],
      "themeKey": "light-social-glow",
      "themeLabelZh": "轻社交微光提气"
    },
    {
      "accentColorSummary": "石墨灰",
      "brandName": "SEZANE",
      "candidatePaletteIds": [],
      "channelType": "marketplace-brand-store",
      "colorSummary": [
        "浅驼",
        "银雾蓝",
        "石墨灰"
      ],
      "digestionStatus": "sampled",
      "finalPaletteIds": [],
      "itemCategory": "skirt",
      "marketSignals": "轻约会和朋友见面更适合把柔粉压进灰感，做成更成熟的现代柔美路线。 SEZANE 更适合柔和提气与女性化但不甜腻的通勤路线。",
      "notes": "自动候选：优先审阅 SEZANE 的 SEZANE 公开店铺检索 入口，重点看 浅驼、银雾蓝与石墨灰的现代柔美层次。",
      "observedAt": "2026-05-09",
      "occasionId": "light-social",
      "platform": "SEZANE 公开店铺检索",
      "primaryColorSummary": "浅驼",
      "productionBatchId": "phase1-light-social-batch01",
      "samplingId": "sam_light-social_b01_012",
      "seasonHint": "spring",
      "secondaryColorSummary": "银雾蓝",
      "sourceId": "candidate-sezane-skirt-sam_light-social_b01_012",
      "sourceUrl": "https://www.google.com/search?q=SEZANE%20women%20skirt%20women%20outfit%20search",
      "styleSignals": [
        "soft",
        "feminine-leaning",
        "womenswear"
      ],
      "themeKey": "light-social-modern-romance",
      "themeLabelZh": "轻社交现代柔美"
    },
    {
      "accentColorSummary": "深藏蓝",
      "brandName": "Massimo Dutti",
      "candidatePaletteIds": [],
      "channelType": "brand-site",
      "colorSummary": [
        "暖壳白",
        "铁灰",
        "深藏蓝"
      ],
      "digestionStatus": "sampled",
      "finalPaletteIds": [],
      "itemCategory": "skirt",
      "marketSignals": "轻晚餐和轻社交不一定都是粉色，珍珠白、烟灰蓝与李紫灰能把精致感拉出来。 Massimo Dutti 更适合暖中性色、轻商务和成熟通勤路线。",
      "notes": "自动候选：优先审阅 Massimo Dutti 的 Massimo Dutti 官网 入口，重点看 暖壳白、铁灰与深藏蓝的精致晚餐层次。",
      "observedAt": "2026-05-09",
      "occasionId": "light-social",
      "platform": "Massimo Dutti 官网",
      "primaryColorSummary": "暖壳白",
      "productionBatchId": "phase1-light-social-batch01",
      "samplingId": "sam_light-social_b01_013",
      "seasonHint": "spring",
      "secondaryColorSummary": "铁灰",
      "sourceId": "candidate-massimo-dutti-skirt-sam_light-social_b01_013",
      "sourceUrl": "https://www.massimodutti.com/",
      "styleSignals": [
        "polished",
        "refined",
        "womenswear"
      ],
      "themeKey": "light-social-polished-dinner",
      "themeLabelZh": "轻社交精致晚餐"
    },
    {
      "accentColorSummary": "浅砖红",
      "brandName": "SEZANE",
      "candidatePaletteIds": [],
      "channelType": "brand-flagship-store",
      "colorSummary": [
        "钢蓝灰",
        "栗棕",
        "浅砖红"
      ],
      "digestionStatus": "sampled",
      "finalPaletteIds": [],
      "itemCategory": "skirt",
      "marketSignals": "轻社交并不总靠粉调，奶油白、浅卡其和鼠尾草灰更适合偏克制的雅致路线。 SEZANE 更适合柔和提气与女性化但不甜腻的通勤路线。",
      "notes": "自动候选：优先审阅 SEZANE 的 SEZANE 公开品牌检索 入口，重点看 钢蓝灰、栗棕与浅砖红的鼠尾草雅致层次。",
      "observedAt": "2026-05-09",
      "occasionId": "light-social",
      "platform": "SEZANE 公开品牌检索",
      "primaryColorSummary": "钢蓝灰",
      "productionBatchId": "phase1-light-social-batch01",
      "samplingId": "sam_light-social_b01_014",
      "seasonHint": "spring",
      "secondaryColorSummary": "栗棕",
      "sourceId": "candidate-sezane-skirt-sam_light-social_b01_014",
      "sourceUrl": "https://www.google.com/search?q=SEZANE%20women%20skirt%20women%20official%20brand%20search",
      "styleSignals": [
        "soft",
        "feminine-leaning",
        "womenswear"
      ],
      "themeKey": "light-social-sage-polish",
      "themeLabelZh": "轻社交鼠尾草雅致"
    },
    {
      "accentColorSummary": "赤陶砖红",
      "brandName": "TOTEME",
      "candidatePaletteIds": [],
      "channelType": "multi-brand-platform",
      "colorSummary": [
        "烟灰蓝",
        "冰米白",
        "赤陶砖红"
      ],
      "digestionStatus": "sampled",
      "finalPaletteIds": [],
      "itemCategory": "skirt",
      "marketSignals": "轻社交的夜间精致路线适合用云雾白、雾灰蓝和墨海军蓝保持克制的存在感。 TOTEME 更适合冷静、低对比、材质感强的女装通勤样本。",
      "notes": "自动候选：优先审阅 TOTEME 的 Net-a-Porter 公开检索 入口，重点看 烟灰蓝、冰米白与赤陶砖红的夜蓝精致层次。",
      "observedAt": "2026-05-09",
      "occasionId": "light-social",
      "platform": "Net-a-Porter 公开检索",
      "primaryColorSummary": "烟灰蓝",
      "productionBatchId": "phase1-light-social-batch01",
      "samplingId": "sam_light-social_b01_015",
      "seasonHint": "spring",
      "secondaryColorSummary": "冰米白",
      "sourceId": "candidate-toteme-skirt-sam_light-social_b01_015",
      "sourceUrl": "https://www.google.com/search?q=site%3Anet-a-porter.com%20TOTEME%20women%20skirt",
      "styleSignals": [
        "quiet",
        "refined",
        "womenswear"
      ],
      "themeKey": "light-social-night-navy",
      "themeLabelZh": "轻社交夜蓝精致"
    },
    {
      "accentColorSummary": "海雾蓝",
      "brandName": "SEZANE",
      "candidatePaletteIds": [],
      "channelType": "marketplace-brand-store",
      "colorSummary": [
        "暖壳白",
        "铁灰",
        "海雾蓝"
      ],
      "digestionStatus": "sampled",
      "finalPaletteIds": [],
      "itemCategory": "cardigan",
      "marketSignals": "轻社交场景需要一点提气，但仍以低饱和豆沙、雾粉杏和奶白为主，避免甜腻。 SEZANE 更适合柔和提气与女性化但不甜腻的通勤路线。",
      "notes": "自动候选：优先审阅 SEZANE 的 SEZANE 公开店铺检索 入口，重点看 暖壳白、铁灰与海雾蓝的轻社交提气层次。",
      "observedAt": "2026-05-09",
      "occasionId": "light-social",
      "platform": "SEZANE 公开店铺检索",
      "primaryColorSummary": "暖壳白",
      "productionBatchId": "phase1-light-social-batch01",
      "samplingId": "sam_light-social_b01_016",
      "seasonHint": "autumn",
      "secondaryColorSummary": "铁灰",
      "sourceId": "candidate-sezane-cardigan-sam_light-social_b01_016",
      "sourceUrl": "https://www.google.com/search?q=SEZANE%20women%20cardigan%20women%20outfit%20search",
      "styleSignals": [
        "soft",
        "feminine-leaning",
        "womenswear"
      ],
      "themeKey": "light-social-glow",
      "themeLabelZh": "轻社交微光提气"
    },
    {
      "accentColorSummary": "苔雾绿",
      "brandName": "SEZANE",
      "candidatePaletteIds": [],
      "channelType": "brand-site",
      "colorSummary": [
        "暖燕麦",
        "暖咖棕",
        "苔雾绿"
      ],
      "digestionStatus": "sampled",
      "finalPaletteIds": [],
      "itemCategory": "cardigan",
      "marketSignals": "轻约会和朋友见面更适合把柔粉压进灰感，做成更成熟的现代柔美路线。 SEZANE 更适合柔和提气与女性化但不甜腻的通勤路线。",
      "notes": "自动候选：优先审阅 SEZANE 的 SEZANE 官网 入口，重点看 暖燕麦、暖咖棕与苔雾绿的现代柔美层次。",
      "observedAt": "2026-05-09",
      "occasionId": "light-social",
      "platform": "SEZANE 官网",
      "primaryColorSummary": "暖燕麦",
      "productionBatchId": "phase1-light-social-batch01",
      "samplingId": "sam_light-social_b01_017",
      "seasonHint": "autumn",
      "secondaryColorSummary": "暖咖棕",
      "sourceId": "candidate-sezane-cardigan-sam_light-social_b01_017",
      "sourceUrl": "https://www.sezane.com/",
      "styleSignals": [
        "soft",
        "feminine-leaning",
        "womenswear"
      ],
      "themeKey": "light-social-modern-romance",
      "themeLabelZh": "轻社交现代柔美"
    },
    {
      "accentColorSummary": "冷海军蓝",
      "brandName": "Massimo Dutti",
      "candidatePaletteIds": [],
      "channelType": "brand-flagship-store",
      "colorSummary": [
        "壳白",
        "钢蓝灰",
        "冷海军蓝"
      ],
      "digestionStatus": "sampled",
      "finalPaletteIds": [],
      "itemCategory": "cardigan",
      "marketSignals": "轻晚餐和轻社交不一定都是粉色，珍珠白、烟灰蓝与李紫灰能把精致感拉出来。 Massimo Dutti 更适合暖中性色、轻商务和成熟通勤路线。",
      "notes": "自动候选：优先审阅 Massimo Dutti 的 Massimo Dutti 公开品牌检索 入口，重点看 壳白、钢蓝灰与冷海军蓝的精致晚餐层次。",
      "observedAt": "2026-05-09",
      "occasionId": "light-social",
      "platform": "Massimo Dutti 公开品牌检索",
      "primaryColorSummary": "壳白",
      "productionBatchId": "phase1-light-social-batch01",
      "samplingId": "sam_light-social_b01_018",
      "seasonHint": "autumn",
      "secondaryColorSummary": "钢蓝灰",
      "sourceId": "candidate-massimo-dutti-cardigan-sam_light-social_b01_018",
      "sourceUrl": "https://www.google.com/search?q=Massimo%20Dutti%20women%20cardigan%20women%20official%20brand%20search",
      "styleSignals": [
        "polished",
        "refined",
        "womenswear"
      ],
      "themeKey": "light-social-polished-dinner",
      "themeLabelZh": "轻社交精致晚餐"
    },
    {
      "accentColorSummary": "茶砖红",
      "brandName": "SEZANE",
      "candidatePaletteIds": [],
      "channelType": "multi-brand-platform",
      "colorSummary": [
        "柔卡其",
        "焦糖棕",
        "茶砖红"
      ],
      "digestionStatus": "sampled",
      "finalPaletteIds": [],
      "itemCategory": "cardigan",
      "marketSignals": "轻社交并不总靠粉调，奶油白、浅卡其和鼠尾草灰更适合偏克制的雅致路线。 SEZANE 更适合柔和提气与女性化但不甜腻的通勤路线。",
      "notes": "自动候选：优先审阅 SEZANE 的 Net-a-Porter 公开检索 入口，重点看 柔卡其、焦糖棕与茶砖红的鼠尾草雅致层次。",
      "observedAt": "2026-05-09",
      "occasionId": "light-social",
      "platform": "Net-a-Porter 公开检索",
      "primaryColorSummary": "柔卡其",
      "productionBatchId": "phase1-light-social-batch01",
      "samplingId": "sam_light-social_b01_019",
      "seasonHint": "autumn",
      "secondaryColorSummary": "焦糖棕",
      "sourceId": "candidate-sezane-cardigan-sam_light-social_b01_019",
      "sourceUrl": "https://www.google.com/search?q=site%3Anet-a-porter.com%20SEZANE%20women%20cardigan",
      "styleSignals": [
        "soft",
        "feminine-leaning",
        "womenswear"
      ],
      "themeKey": "light-social-sage-polish",
      "themeLabelZh": "轻社交鼠尾草雅致"
    },
    {
      "accentColorSummary": "栗棕",
      "brandName": "Theory",
      "candidatePaletteIds": [],
      "channelType": "marketplace-brand-store",
      "colorSummary": [
        "雾灰蓝",
        "燕麦驼",
        "栗棕"
      ],
      "digestionStatus": "sampled",
      "finalPaletteIds": [],
      "itemCategory": "cardigan",
      "marketSignals": "轻社交的夜间精致路线适合用云雾白、雾灰蓝和墨海军蓝保持克制的存在感。 Theory 更适合剪裁明确、冷静专业的女装通勤样本。",
      "notes": "自动候选：优先审阅 Theory 的 Theory 公开店铺检索 入口，重点看 雾灰蓝、燕麦驼与栗棕的夜蓝精致层次。",
      "observedAt": "2026-05-09",
      "occasionId": "light-social",
      "platform": "Theory 公开店铺检索",
      "primaryColorSummary": "雾灰蓝",
      "productionBatchId": "phase1-light-social-batch01",
      "samplingId": "sam_light-social_b01_020",
      "seasonHint": "autumn",
      "secondaryColorSummary": "燕麦驼",
      "sourceId": "candidate-theory-cardigan-sam_light-social_b01_020",
      "sourceUrl": "https://www.google.com/search?q=Theory%20women%20cardigan%20women%20outfit%20search",
      "styleSignals": [
        "tailored",
        "sharp",
        "womenswear"
      ],
      "themeKey": "light-social-night-navy",
      "themeLabelZh": "轻社交夜蓝精致"
    },
    {
      "accentColorSummary": "焦糖棕",
      "brandName": "Vince",
      "candidatePaletteIds": [],
      "channelType": "brand-site",
      "colorSummary": [
        "浅驼",
        "银雾蓝",
        "焦糖棕"
      ],
      "digestionStatus": "sampled",
      "finalPaletteIds": [],
      "itemCategory": "knitwear",
      "marketSignals": "轻社交场景需要一点提气，但仍以低饱和豆沙、雾粉杏和奶白为主，避免甜腻。 Vince 更适合柔和中性色和都市暖稳路线。",
      "notes": "自动候选：优先审阅 Vince 的 Vince 官网 入口，重点看 浅驼、银雾蓝与焦糖棕的轻社交提气层次。",
      "observedAt": "2026-05-09",
      "occasionId": "light-social",
      "platform": "Vince 官网",
      "primaryColorSummary": "浅驼",
      "productionBatchId": "phase1-light-social-batch01",
      "samplingId": "sam_light-social_b01_021",
      "seasonHint": "winter",
      "secondaryColorSummary": "银雾蓝",
      "sourceId": "candidate-vince-knitwear-sam_light-social_b01_021",
      "sourceUrl": "https://www.vince.com/",
      "styleSignals": [
        "soft",
        "grounded",
        "womenswear"
      ],
      "themeKey": "light-social-glow",
      "themeLabelZh": "轻社交微光提气"
    },
    {
      "accentColorSummary": "深雾灰",
      "brandName": "Vince",
      "candidatePaletteIds": [],
      "channelType": "brand-flagship-store",
      "colorSummary": [
        "暖壳白",
        "摩卡棕",
        "深雾灰"
      ],
      "digestionStatus": "sampled",
      "finalPaletteIds": [],
      "itemCategory": "knitwear",
      "marketSignals": "轻约会和朋友见面更适合把柔粉压进灰感，做成更成熟的现代柔美路线。 Vince 更适合柔和中性色和都市暖稳路线。",
      "notes": "自动候选：优先审阅 Vince 的 Vince 公开品牌检索 入口，重点看 暖壳白、摩卡棕与深雾灰的现代柔美层次。",
      "observedAt": "2026-05-09",
      "occasionId": "light-social",
      "platform": "Vince 公开品牌检索",
      "primaryColorSummary": "暖壳白",
      "productionBatchId": "phase1-light-social-batch01",
      "samplingId": "sam_light-social_b01_022",
      "seasonHint": "winter",
      "secondaryColorSummary": "摩卡棕",
      "sourceId": "candidate-vince-knitwear-sam_light-social_b01_022",
      "sourceUrl": "https://www.google.com/search?q=Vince%20women%20knitwear%20women%20official%20brand%20search",
      "styleSignals": [
        "soft",
        "grounded",
        "womenswear"
      ],
      "themeKey": "light-social-modern-romance",
      "themeLabelZh": "轻社交现代柔美"
    },
    {
      "accentColorSummary": "深砖红",
      "brandName": "Theory",
      "candidatePaletteIds": [],
      "channelType": "multi-brand-platform",
      "colorSummary": [
        "浅卡其",
        "云雾白",
        "深砖红"
      ],
      "digestionStatus": "sampled",
      "finalPaletteIds": [],
      "itemCategory": "knitwear",
      "marketSignals": "轻晚餐和轻社交不一定都是粉色，珍珠白、烟灰蓝与李紫灰能把精致感拉出来。 Theory 更适合剪裁明确、冷静专业的女装通勤样本。",
      "notes": "自动候选：优先审阅 Theory 的 Net-a-Porter 公开检索 入口，重点看 浅卡其、云雾白与深砖红的精致晚餐层次。",
      "observedAt": "2026-05-09",
      "occasionId": "light-social",
      "platform": "Net-a-Porter 公开检索",
      "primaryColorSummary": "浅卡其",
      "productionBatchId": "phase1-light-social-batch01",
      "samplingId": "sam_light-social_b01_023",
      "seasonHint": "winter",
      "secondaryColorSummary": "云雾白",
      "sourceId": "candidate-theory-knitwear-sam_light-social_b01_023",
      "sourceUrl": "https://www.google.com/search?q=site%3Anet-a-porter.com%20Theory%20women%20knitwear",
      "styleSignals": [
        "tailored",
        "sharp",
        "womenswear"
      ],
      "themeKey": "light-social-polished-dinner",
      "themeLabelZh": "轻社交精致晚餐"
    },
    {
      "accentColorSummary": "冷橄榄灰",
      "brandName": "UNIQLO",
      "candidatePaletteIds": [],
      "channelType": "marketplace-brand-store",
      "colorSummary": [
        "浅钢蓝",
        "奶驼",
        "冷橄榄灰"
      ],
      "digestionStatus": "sampled",
      "finalPaletteIds": [],
      "itemCategory": "knitwear",
      "marketSignals": "轻社交并不总靠粉调，奶油白、浅卡其和鼠尾草灰更适合偏克制的雅致路线。 UNIQLO 可以补大众通勤基础款的颜色分布与保守安全样本。",
      "notes": "自动候选：优先审阅 UNIQLO 的 UNIQLO 公开店铺检索 入口，重点看 浅钢蓝、奶驼与冷橄榄灰的鼠尾草雅致层次。",
      "observedAt": "2026-05-09",
      "occasionId": "light-social",
      "platform": "UNIQLO 公开店铺检索",
      "primaryColorSummary": "浅钢蓝",
      "productionBatchId": "phase1-light-social-batch01",
      "samplingId": "sam_light-social_b01_024",
      "seasonHint": "winter",
      "secondaryColorSummary": "奶驼",
      "sourceId": "candidate-uniqlo-knitwear-sam_light-social_b01_024",
      "sourceUrl": "https://www.google.com/search?q=UNIQLO%20women%20knitwear%20women%20outfit%20search",
      "styleSignals": [
        "daily",
        "commute",
        "womenswear"
      ],
      "themeKey": "light-social-sage-polish",
      "themeLabelZh": "轻社交鼠尾草雅致"
    },
    {
      "accentColorSummary": "藏蓝黑",
      "brandName": "TOTEME",
      "candidatePaletteIds": [],
      "channelType": "brand-site",
      "colorSummary": [
        "沙色卡其",
        "冷石墨",
        "藏蓝黑"
      ],
      "digestionStatus": "sampled",
      "finalPaletteIds": [],
      "itemCategory": "knitwear",
      "marketSignals": "轻社交的夜间精致路线适合用云雾白、雾灰蓝和墨海军蓝保持克制的存在感。 TOTEME 更适合冷静、低对比、材质感强的女装通勤样本。",
      "notes": "自动候选：优先审阅 TOTEME 的 TOTEME 官网 入口，重点看 沙色卡其、冷石墨与藏蓝黑的夜蓝精致层次。",
      "observedAt": "2026-05-09",
      "occasionId": "light-social",
      "platform": "TOTEME 官网",
      "primaryColorSummary": "沙色卡其",
      "productionBatchId": "phase1-light-social-batch01",
      "samplingId": "sam_light-social_b01_025",
      "seasonHint": "winter",
      "secondaryColorSummary": "冷石墨",
      "sourceId": "candidate-toteme-knitwear-sam_light-social_b01_025",
      "sourceUrl": "https://toteme.com/",
      "styleSignals": [
        "quiet",
        "refined",
        "womenswear"
      ],
      "themeKey": "light-social-night-navy",
      "themeLabelZh": "轻社交夜蓝精致"
    },
    {
      "accentColorSummary": "石墨灰",
      "brandName": "Vince",
      "candidatePaletteIds": [],
      "channelType": "brand-flagship-store",
      "colorSummary": [
        "冰米白",
        "银雾蓝",
        "石墨灰"
      ],
      "digestionStatus": "sampled",
      "finalPaletteIds": [],
      "itemCategory": "blazer",
      "marketSignals": "轻社交场景需要一点提气，但仍以低饱和豆沙、雾粉杏和奶白为主，避免甜腻。 Vince 更适合柔和中性色和都市暖稳路线。",
      "notes": "自动候选：优先审阅 Vince 的 Vince 公开品牌检索 入口，重点看 冰米白、银雾蓝与石墨灰的轻社交提气层次。",
      "observedAt": "2026-05-09",
      "occasionId": "light-social",
      "platform": "Vince 公开品牌检索",
      "primaryColorSummary": "冰米白",
      "productionBatchId": "phase1-light-social-batch01",
      "samplingId": "sam_light-social_b01_026",
      "seasonHint": "spring",
      "secondaryColorSummary": "银雾蓝",
      "sourceId": "candidate-vince-blazer-sam_light-social_b01_026",
      "sourceUrl": "https://www.google.com/search?q=Vince%20women%20blazer%20women%20official%20brand%20search",
      "styleSignals": [
        "soft",
        "grounded",
        "womenswear"
      ],
      "themeKey": "light-social-glow",
      "themeLabelZh": "轻社交微光提气"
    },
    {
      "accentColorSummary": "赤陶红",
      "brandName": "Vince",
      "candidatePaletteIds": [],
      "channelType": "multi-brand-platform",
      "colorSummary": [
        "浅钢蓝",
        "橡木棕",
        "赤陶红"
      ],
      "digestionStatus": "sampled",
      "finalPaletteIds": [],
      "itemCategory": "blazer",
      "marketSignals": "轻约会和朋友见面更适合把柔粉压进灰感，做成更成熟的现代柔美路线。 Vince 更适合柔和中性色和都市暖稳路线。",
      "notes": "自动候选：优先审阅 Vince 的 Net-a-Porter 公开检索 入口，重点看 浅钢蓝、橡木棕与赤陶红的现代柔美层次。",
      "observedAt": "2026-05-09",
      "occasionId": "light-social",
      "platform": "Net-a-Porter 公开检索",
      "primaryColorSummary": "浅钢蓝",
      "productionBatchId": "phase1-light-social-batch01",
      "samplingId": "sam_light-social_b01_027",
      "seasonHint": "spring",
      "secondaryColorSummary": "橡木棕",
      "sourceId": "candidate-vince-blazer-sam_light-social_b01_027",
      "sourceUrl": "https://www.google.com/search?q=site%3Anet-a-porter.com%20Vince%20women%20blazer",
      "styleSignals": [
        "soft",
        "grounded",
        "womenswear"
      ],
      "themeKey": "light-social-modern-romance",
      "themeLabelZh": "轻社交现代柔美"
    },
    {
      "accentColorSummary": "深焦糖棕",
      "brandName": "Theory",
      "candidatePaletteIds": [],
      "channelType": "marketplace-brand-store",
      "colorSummary": [
        "云雾白",
        "冷雾蓝",
        "深焦糖棕"
      ],
      "digestionStatus": "sampled",
      "finalPaletteIds": [],
      "itemCategory": "blazer",
      "marketSignals": "轻晚餐和轻社交不一定都是粉色，珍珠白、烟灰蓝与李紫灰能把精致感拉出来。 Theory 更适合剪裁明确、冷静专业的女装通勤样本。",
      "notes": "自动候选：优先审阅 Theory 的 Theory 公开店铺检索 入口，重点看 云雾白、冷雾蓝与深焦糖棕的精致晚餐层次。",
      "observedAt": "2026-05-09",
      "occasionId": "light-social",
      "platform": "Theory 公开店铺检索",
      "primaryColorSummary": "云雾白",
      "productionBatchId": "phase1-light-social-batch01",
      "samplingId": "sam_light-social_b01_028",
      "seasonHint": "spring",
      "secondaryColorSummary": "冷雾蓝",
      "sourceId": "candidate-theory-blazer-sam_light-social_b01_028",
      "sourceUrl": "https://www.google.com/search?q=Theory%20women%20blazer%20women%20outfit%20search",
      "styleSignals": [
        "tailored",
        "sharp",
        "womenswear"
      ],
      "themeKey": "light-social-polished-dinner",
      "themeLabelZh": "轻社交精致晚餐"
    },
    {
      "accentColorSummary": "烟炭灰",
      "brandName": "SEZANE",
      "candidatePaletteIds": [],
      "channelType": "brand-site",
      "colorSummary": [
        "烟灰蓝",
        "浅驼",
        "烟炭灰"
      ],
      "digestionStatus": "sampled",
      "finalPaletteIds": [],
      "itemCategory": "blazer",
      "marketSignals": "轻社交并不总靠粉调，奶油白、浅卡其和鼠尾草灰更适合偏克制的雅致路线。 SEZANE 更适合柔和提气与女性化但不甜腻的通勤路线。",
      "notes": "自动候选：优先审阅 SEZANE 的 SEZANE 官网 入口，重点看 烟灰蓝、浅驼与烟炭灰的鼠尾草雅致层次。",
      "observedAt": "2026-05-09",
      "occasionId": "light-social",
      "platform": "SEZANE 官网",
      "primaryColorSummary": "烟灰蓝",
      "productionBatchId": "phase1-light-social-batch01",
      "samplingId": "sam_light-social_b01_029",
      "seasonHint": "spring",
      "secondaryColorSummary": "浅驼",
      "sourceId": "candidate-sezane-blazer-sam_light-social_b01_029",
      "sourceUrl": "https://www.sezane.com/",
      "styleSignals": [
        "soft",
        "feminine-leaning",
        "womenswear"
      ],
      "themeKey": "light-social-sage-polish",
      "themeLabelZh": "轻社交鼠尾草雅致"
    },
    {
      "accentColorSummary": "铁灰",
      "brandName": "Theory",
      "candidatePaletteIds": [],
      "channelType": "brand-flagship-store",
      "colorSummary": [
        "浅钢蓝",
        "暖壳白",
        "铁灰"
      ],
      "digestionStatus": "sampled",
      "finalPaletteIds": [],
      "itemCategory": "blazer",
      "marketSignals": "轻社交的夜间精致路线适合用云雾白、雾灰蓝和墨海军蓝保持克制的存在感。 Theory 更适合剪裁明确、冷静专业的女装通勤样本。",
      "notes": "自动候选：优先审阅 Theory 的 Theory 公开品牌检索 入口，重点看 浅钢蓝、暖壳白与铁灰的夜蓝精致层次。",
      "observedAt": "2026-05-09",
      "occasionId": "light-social",
      "platform": "Theory 公开品牌检索",
      "primaryColorSummary": "浅钢蓝",
      "productionBatchId": "phase1-light-social-batch01",
      "samplingId": "sam_light-social_b01_030",
      "seasonHint": "spring",
      "secondaryColorSummary": "暖壳白",
      "sourceId": "candidate-theory-blazer-sam_light-social_b01_030",
      "sourceUrl": "https://www.google.com/search?q=Theory%20women%20blazer%20women%20official%20brand%20search",
      "styleSignals": [
        "tailored",
        "sharp",
        "womenswear"
      ],
      "themeKey": "light-social-night-navy",
      "themeLabelZh": "轻社交夜蓝精致"
    },
    {
      "accentColorSummary": "板岩灰",
      "brandName": "Vince",
      "candidatePaletteIds": [],
      "channelType": "multi-brand-platform",
      "colorSummary": [
        "雾米白",
        "灰卡其",
        "板岩灰"
      ],
      "digestionStatus": "sampled",
      "finalPaletteIds": [],
      "itemCategory": "shirt",
      "marketSignals": "轻社交场景需要一点提气，但仍以低饱和豆沙、雾粉杏和奶白为主，避免甜腻。 Vince 更适合柔和中性色和都市暖稳路线。",
      "notes": "自动候选：优先审阅 Vince 的 Net-a-Porter 公开检索 入口，重点看 雾米白、灰卡其与板岩灰的轻社交提气层次。",
      "observedAt": "2026-05-09",
      "occasionId": "light-social",
      "platform": "Net-a-Porter 公开检索",
      "primaryColorSummary": "雾米白",
      "productionBatchId": "phase1-light-social-batch01",
      "samplingId": "sam_light-social_b01_031",
      "seasonHint": "spring",
      "secondaryColorSummary": "灰卡其",
      "sourceId": "candidate-vince-shirt-sam_light-social_b01_031",
      "sourceUrl": "https://www.google.com/search?q=site%3Anet-a-porter.com%20Vince%20women%20shirt",
      "styleSignals": [
        "soft",
        "grounded",
        "womenswear"
      ],
      "themeKey": "light-social-glow",
      "themeLabelZh": "轻社交微光提气"
    },
    {
      "accentColorSummary": "摩卡棕",
      "brandName": "SEZANE",
      "candidatePaletteIds": [],
      "channelType": "marketplace-brand-store",
      "colorSummary": [
        "灰卡其",
        "暖壳白",
        "摩卡棕"
      ],
      "digestionStatus": "sampled",
      "finalPaletteIds": [],
      "itemCategory": "shirt",
      "marketSignals": "轻约会和朋友见面更适合把柔粉压进灰感，做成更成熟的现代柔美路线。 SEZANE 更适合柔和提气与女性化但不甜腻的通勤路线。",
      "notes": "自动候选：优先审阅 SEZANE 的 SEZANE 公开店铺检索 入口，重点看 灰卡其、暖壳白与摩卡棕的现代柔美层次。",
      "observedAt": "2026-05-09",
      "occasionId": "light-social",
      "platform": "SEZANE 公开店铺检索",
      "primaryColorSummary": "灰卡其",
      "productionBatchId": "phase1-light-social-batch01",
      "samplingId": "sam_light-social_b01_032",
      "seasonHint": "spring",
      "secondaryColorSummary": "暖壳白",
      "sourceId": "candidate-sezane-shirt-sam_light-social_b01_032",
      "sourceUrl": "https://www.google.com/search?q=SEZANE%20women%20shirt%20women%20outfit%20search",
      "styleSignals": [
        "soft",
        "feminine-leaning",
        "womenswear"
      ],
      "themeKey": "light-social-modern-romance",
      "themeLabelZh": "轻社交现代柔美"
    },
    {
      "accentColorSummary": "暖赤陶",
      "brandName": "Massimo Dutti",
      "candidatePaletteIds": [],
      "channelType": "brand-site",
      "colorSummary": [
        "奶驼",
        "铁灰",
        "暖赤陶"
      ],
      "digestionStatus": "sampled",
      "finalPaletteIds": [],
      "itemCategory": "shirt",
      "marketSignals": "轻晚餐和轻社交不一定都是粉色，珍珠白、烟灰蓝与李紫灰能把精致感拉出来。 Massimo Dutti 更适合暖中性色、轻商务和成熟通勤路线。",
      "notes": "自动候选：优先审阅 Massimo Dutti 的 Massimo Dutti 官网 入口，重点看 奶驼、铁灰与暖赤陶的精致晚餐层次。",
      "observedAt": "2026-05-09",
      "occasionId": "light-social",
      "platform": "Massimo Dutti 官网",
      "primaryColorSummary": "奶驼",
      "productionBatchId": "phase1-light-social-batch01",
      "samplingId": "sam_light-social_b01_033",
      "seasonHint": "spring",
      "secondaryColorSummary": "铁灰",
      "sourceId": "candidate-massimo-dutti-shirt-sam_light-social_b01_033",
      "sourceUrl": "https://www.massimodutti.com/",
      "styleSignals": [
        "polished",
        "refined",
        "womenswear"
      ],
      "themeKey": "light-social-polished-dinner",
      "themeLabelZh": "轻社交精致晚餐"
    },
    {
      "accentColorSummary": "栗棕",
      "brandName": "UNIQLO",
      "candidatePaletteIds": [],
      "channelType": "brand-flagship-store",
      "colorSummary": [
        "雾灰蓝",
        "鼠尾草灰",
        "栗棕"
      ],
      "digestionStatus": "sampled",
      "finalPaletteIds": [],
      "itemCategory": "shirt",
      "marketSignals": "轻社交并不总靠粉调，奶油白、浅卡其和鼠尾草灰更适合偏克制的雅致路线。 UNIQLO 可以补大众通勤基础款的颜色分布与保守安全样本。",
      "notes": "自动候选：优先审阅 UNIQLO 的 UNIQLO 公开品牌检索 入口，重点看 雾灰蓝、鼠尾草灰与栗棕的鼠尾草雅致层次。",
      "observedAt": "2026-05-09",
      "occasionId": "light-social",
      "platform": "UNIQLO 公开品牌检索",
      "primaryColorSummary": "雾灰蓝",
      "productionBatchId": "phase1-light-social-batch01",
      "samplingId": "sam_light-social_b01_034",
      "seasonHint": "spring",
      "secondaryColorSummary": "鼠尾草灰",
      "sourceId": "candidate-uniqlo-shirt-sam_light-social_b01_034",
      "sourceUrl": "https://www.google.com/search?q=UNIQLO%20women%20shirt%20women%20official%20brand%20search",
      "styleSignals": [
        "daily",
        "commute",
        "womenswear"
      ],
      "themeKey": "light-social-sage-polish",
      "themeLabelZh": "轻社交鼠尾草雅致"
    },
    {
      "accentColorSummary": "藏蓝黑",
      "brandName": "Theory",
      "candidatePaletteIds": [],
      "channelType": "multi-brand-platform",
      "colorSummary": [
        "冷雾蓝",
        "珍珠白",
        "藏蓝黑"
      ],
      "digestionStatus": "sampled",
      "finalPaletteIds": [],
      "itemCategory": "shirt",
      "marketSignals": "轻社交的夜间精致路线适合用云雾白、雾灰蓝和墨海军蓝保持克制的存在感。 Theory 更适合剪裁明确、冷静专业的女装通勤样本。",
      "notes": "自动候选：优先审阅 Theory 的 Net-a-Porter 公开检索 入口，重点看 冷雾蓝、珍珠白与藏蓝黑的夜蓝精致层次。",
      "observedAt": "2026-05-09",
      "occasionId": "light-social",
      "platform": "Net-a-Porter 公开检索",
      "primaryColorSummary": "冷雾蓝",
      "productionBatchId": "phase1-light-social-batch01",
      "samplingId": "sam_light-social_b01_035",
      "seasonHint": "spring",
      "secondaryColorSummary": "珍珠白",
      "sourceId": "candidate-theory-shirt-sam_light-social_b01_035",
      "sourceUrl": "https://www.google.com/search?q=site%3Anet-a-porter.com%20Theory%20women%20shirt",
      "styleSignals": [
        "tailored",
        "sharp",
        "womenswear"
      ],
      "themeKey": "light-social-night-navy",
      "themeLabelZh": "轻社交夜蓝精致"
    },
    {
      "accentColorSummary": "茶砖红",
      "brandName": "SEZANE",
      "candidatePaletteIds": [],
      "channelType": "marketplace-brand-store",
      "colorSummary": [
        "霜白",
        "焦糖棕",
        "茶砖红"
      ],
      "digestionStatus": "sampled",
      "finalPaletteIds": [],
      "itemCategory": "trousers",
      "marketSignals": "轻社交场景需要一点提气，但仍以低饱和豆沙、雾粉杏和奶白为主，避免甜腻。 SEZANE 更适合柔和提气与女性化但不甜腻的通勤路线。",
      "notes": "自动候选：优先审阅 SEZANE 的 SEZANE 公开店铺检索 入口，重点看 霜白、焦糖棕与茶砖红的轻社交提气层次。",
      "observedAt": "2026-05-09",
      "occasionId": "light-social",
      "platform": "SEZANE 公开店铺检索",
      "primaryColorSummary": "霜白",
      "productionBatchId": "phase1-light-social-batch01",
      "samplingId": "sam_light-social_b01_036",
      "seasonHint": "all",
      "secondaryColorSummary": "焦糖棕",
      "sourceId": "candidate-sezane-trousers-sam_light-social_b01_036",
      "sourceUrl": "https://www.google.com/search?q=SEZANE%20women%20trousers%20women%20outfit%20search",
      "styleSignals": [
        "soft",
        "feminine-leaning",
        "womenswear"
      ],
      "themeKey": "light-social-glow",
      "themeLabelZh": "轻社交微光提气"
    },
    {
      "accentColorSummary": "浅砖红",
      "brandName": "Vince",
      "candidatePaletteIds": [],
      "channelType": "brand-site",
      "colorSummary": [
        "云雾白",
        "冷雾蓝",
        "浅砖红"
      ],
      "digestionStatus": "sampled",
      "finalPaletteIds": [],
      "itemCategory": "trousers",
      "marketSignals": "轻约会和朋友见面更适合把柔粉压进灰感，做成更成熟的现代柔美路线。 Vince 更适合柔和中性色和都市暖稳路线。",
      "notes": "自动候选：优先审阅 Vince 的 Vince 官网 入口，重点看 云雾白、冷雾蓝与浅砖红的现代柔美层次。",
      "observedAt": "2026-05-09",
      "occasionId": "light-social",
      "platform": "Vince 官网",
      "primaryColorSummary": "云雾白",
      "productionBatchId": "phase1-light-social-batch01",
      "samplingId": "sam_light-social_b01_037",
      "seasonHint": "all",
      "secondaryColorSummary": "冷雾蓝",
      "sourceId": "candidate-vince-trousers-sam_light-social_b01_037",
      "sourceUrl": "https://www.vince.com/",
      "styleSignals": [
        "soft",
        "grounded",
        "womenswear"
      ],
      "themeKey": "light-social-modern-romance",
      "themeLabelZh": "轻社交现代柔美"
    },
    {
      "accentColorSummary": "板岩灰",
      "brandName": "Theory",
      "candidatePaletteIds": [],
      "channelType": "brand-flagship-store",
      "colorSummary": [
        "雾米白",
        "浅钢蓝",
        "板岩灰"
      ],
      "digestionStatus": "sampled",
      "finalPaletteIds": [],
      "itemCategory": "trousers",
      "marketSignals": "轻晚餐和轻社交不一定都是粉色，珍珠白、烟灰蓝与李紫灰能把精致感拉出来。 Theory 更适合剪裁明确、冷静专业的女装通勤样本。",
      "notes": "自动候选：优先审阅 Theory 的 Theory 公开品牌检索 入口，重点看 雾米白、浅钢蓝与板岩灰的精致晚餐层次。",
      "observedAt": "2026-05-09",
      "occasionId": "light-social",
      "platform": "Theory 公开品牌检索",
      "primaryColorSummary": "雾米白",
      "productionBatchId": "phase1-light-social-batch01",
      "samplingId": "sam_light-social_b01_038",
      "seasonHint": "all",
      "secondaryColorSummary": "浅钢蓝",
      "sourceId": "candidate-theory-trousers-sam_light-social_b01_038",
      "sourceUrl": "https://www.google.com/search?q=Theory%20women%20trousers%20women%20official%20brand%20search",
      "styleSignals": [
        "tailored",
        "sharp",
        "womenswear"
      ],
      "themeKey": "light-social-polished-dinner",
      "themeLabelZh": "轻社交精致晚餐"
    },
    {
      "accentColorSummary": "雾砖红",
      "brandName": "UNIQLO",
      "candidatePaletteIds": [],
      "channelType": "multi-brand-platform",
      "colorSummary": [
        "冷雾蓝",
        "橄榄雾灰",
        "雾砖红"
      ],
      "digestionStatus": "sampled",
      "finalPaletteIds": [],
      "itemCategory": "trousers",
      "marketSignals": "轻社交并不总靠粉调，奶油白、浅卡其和鼠尾草灰更适合偏克制的雅致路线。 UNIQLO 可以补大众通勤基础款的颜色分布与保守安全样本。",
      "notes": "自动候选：优先审阅 UNIQLO 的 Net-a-Porter 公开检索 入口，重点看 冷雾蓝、橄榄雾灰与雾砖红的鼠尾草雅致层次。",
      "observedAt": "2026-05-09",
      "occasionId": "light-social",
      "platform": "Net-a-Porter 公开检索",
      "primaryColorSummary": "冷雾蓝",
      "productionBatchId": "phase1-light-social-batch01",
      "samplingId": "sam_light-social_b01_039",
      "seasonHint": "all",
      "secondaryColorSummary": "橄榄雾灰",
      "sourceId": "candidate-uniqlo-trousers-sam_light-social_b01_039",
      "sourceUrl": "https://www.google.com/search?q=site%3Anet-a-porter.com%20UNIQLO%20women%20trousers",
      "styleSignals": [
        "daily",
        "commute",
        "womenswear"
      ],
      "themeKey": "light-social-sage-polish",
      "themeLabelZh": "轻社交鼠尾草雅致"
    },
    {
      "accentColorSummary": "橡木棕",
      "brandName": "Theory",
      "candidatePaletteIds": [],
      "channelType": "marketplace-brand-store",
      "colorSummary": [
        "雾米白",
        "浅钢蓝",
        "橡木棕"
      ],
      "digestionStatus": "sampled",
      "finalPaletteIds": [],
      "itemCategory": "trousers",
      "marketSignals": "轻社交的夜间精致路线适合用云雾白、雾灰蓝和墨海军蓝保持克制的存在感。 Theory 更适合剪裁明确、冷静专业的女装通勤样本。",
      "notes": "自动候选：优先审阅 Theory 的 Theory 公开店铺检索 入口，重点看 雾米白、浅钢蓝与橡木棕的夜蓝精致层次。",
      "observedAt": "2026-05-09",
      "occasionId": "light-social",
      "platform": "Theory 公开店铺检索",
      "primaryColorSummary": "雾米白",
      "productionBatchId": "phase1-light-social-batch01",
      "samplingId": "sam_light-social_b01_040",
      "seasonHint": "all",
      "secondaryColorSummary": "浅钢蓝",
      "sourceId": "candidate-theory-trousers-sam_light-social_b01_040",
      "sourceUrl": "https://www.google.com/search?q=Theory%20women%20trousers%20women%20outfit%20search",
      "styleSignals": [
        "tailored",
        "sharp",
        "womenswear"
      ],
      "themeKey": "light-social-night-navy",
      "themeLabelZh": "轻社交夜蓝精致"
    }
  ],
  "summary": {
    "completedCount": 40,
    "recordCount": 40,
    "remainingVisibleUniqueCapacity": 21,
    "uniqueBrandCount": 6,
    "uniquePlatformCount": 13,
    "visibleUniqueCapacity": 61,
    "visibleUniqueCount": 40
  },
  "updatedAt": "2026-05-09T09:26:11.151Z",
  "version": 2
}
